hello_python_world/__init__.py
hello_python_world/hello_python_world.py
hello_python_world-0.0.13.dist-info/LICENSE
hello_python_world-0.0.13.dist-info/METADATA
hello_python_world-0.0.13.dist-info/WHEEL
hello_python_world-0.0.13.dist-info/top_level.txt
hello_python_world-0.0.13.dist-info/RECORD
