Metadata-Version: 2.1
Name: hello-python-world
Version: 0.0.13
Summary: The Hello Python World module
Home-page: https://github.com/mbiemann/hello-python-world
Author: Marcell Biemann
Author-email: mbiemann@gmail.com
License: UNKNOWN
Project-URL: Bug Tracker, https://github.com/mbiemann/hello-python-world/issues
Platform: UNKNOWN
Classifier: Programming Language :: Python :: 3
Classifier: License :: OSI Approved :: MIT License
Classifier: Operating System :: OS Independent
Requires-Python: >=3.6
License-File: LICENSE
